Workbook
Name __xlnm_Print_Area_1: #REF!

Sheet Organograma

Sheet Cálculos da Operação
G4: Cálculos tributários
G5: 21 de maio de 2025
B10: Premissas econômicas
B12: Patrimonio Liquido | E12: Informações Adicionais
B13: SAVIAN | C13: 127 | E13: Data-base dos balanços | I13: 30.06.2026
B14: Invest. Embracon | C14: 127 | E14: Unidade | I14: R$ milhões
E15: Participação das Partes CNP na incorporação (relação de troca) | I15: 0.138
B16: JVFJ | C16: 127 | E16: Participação-alvo final das Partes na CNPH | I16: 0.4
B17: Invest. Embracon | C17: 127 | E17: IRPJ/CSLL — ganho de capital PJ | I17: 0.34
B19: EMBRACON | C19: 254
B20: SAVIAN | C20: =C16/C19 -> 0.5
B21: JVFJ | C21: =C16/C19 -> 0.5
B23: CNPH | C23: 800
B24: Valor de Mercado CNPH | C24: 822
B26: 1) Incorporação CNPH
B28: Participação Societária (Embracon)
C29: Antes | D29: Após Inc
B30: SAVIAN | C30: 0.5 | D30: =C30*(1-I15) -> 0.431
B31: JVFJ | C31: 0.5 | D31: =C31*(1-I15) -> 0.431
B32: CNP (ações novas) | C32: - | D32: =I15 -> 0.138
D33: =SUM(D30:D32) -> 1
B35: Embracon - Incorporação do Acervo
B36: EMBRACON | C36: =C19 -> 254 | D36: =C36/C$38 -> 0.23605948
B37: CNPH | C37: =C24 -> 822 | D37: =C37/C$38 -> 0.76394052
B38: (=) Total | C38: =C36+C37 -> 1076 | D38: =D36+D37 -> 1
B40: PL Embracon (pós inc) | C40: =C41+C42+C43 -> 1076
B41: SAVIAN | C41: =D30*C38 -> 463.756
B42: JVFJ | C42: =D31*C38 -> 463.756
B43: CNP | C43: =D32*C38 -> 148.488
B45: Reflexo nas Holdings (MEP) - Custo de Investimento | H45: Lançamentos Contábeis (Holdings)
D46: SAVIAN | E46: JVFJ | F46: Total | I46: Débitos | J46: Crédito
B47: Custo Original (Investimento anterior) | D47: =C14 -> 127 | E47: =C14 -> 127 | F47: =D47+E47 -> 254 | H47: Reflexo da Incorporação | I47: =D48 -> 411
B48: (+) Incorporação base | D48: =C37/2 -> 411 | E48: =C37/2 -> 411 | F48: =D48+E48 -> 822 | H48: Perda de diluição | J48: =D49 -> -74.244
B49: (-) Diluição (13,8%) | D49: =-(D47+D48)*I15 -> -74.244 | E49: =-(E47+E48)*I15 -> -74.244 | F49: =D49+E49 -> -148.488 | H49: (=) Efeito Líquido do Investimento | J49: =I47+J48 -> 336.756
B50: (=) Parcela liquida incorporada | D50: =D48+D49 -> 336.756 | E50: =E48+E49 -> 336.756 | F50: =D50+E50 -> 673.512
B52: Custo do Investimento Incrementado (Alternativa)
B53: (=) Custo Incrementado | D53: 2 x 463,75 -> | E53: =2*(D54+D55) -> 927.512
B54: Custo Original | D54: =C14 -> 127 | E54: =C17 -> 127
B55: Acervo liquido incorporado | D55: =D50 -> 336.756 | E55: =E50 -> 336.756
B58: 2) Cash-out - Simultânea
B60: Participação por holding pós inc | D60: =D30 -> 0.431
B62: Alienação total estimada | D62: =I16 -> 0.4
B63: Incorporação | D63: =I15 -> 0.138
B64: Percentual de Venda (Cash Out) | D64: =D62-D63 -> 0.262
B65: Por Holding | D65: =D64/2 -> 0.131
B66: Valor estimado Cash-Out (Preço) | D66: 1200
B67: SAVIAN | D67: =D66/2 -> 600
B68: JVFJ | D68: =D66/2 -> 600
B69: Fração Alienada (Cash-Out) | D69: =D65/D60 -> 0.30394432
B71: Alteração na participação da Embracon
C72: Pós Inc | D72: Venda (Cash-Out) | F72: Final
B73: SAVIAN | C73: =D30 -> 0.431 | D73: =-D64/2 -> -0.131 | F73: =C73+D73 -> 0.3
B74: JVFJ | C74: =D31 -> 0.431 | D74: =-D64/2 -> -0.131 | F74: =C74+D74 -> 0.3
B75: CNP | C75: =D32 -> 0.138 | D75: =D64 -> 0.262 | F75: =C75+D75 -> 0.4
B76: (=) Total | C76: =SUM(C73:C75) -> 1 | D76: =SUM(D73:E75) -> 0 | F76: =SUM(F73:F75) -> 1
B78: Cálculo Ganho de Capital (Holdings) | I78: Total
B79: Item | C79: Cenário A (original) | E79: Cenário B (incrementado) | I79: Cen A | J79: Cen B
B80: Preço (Cash-out) | C80: 600 | E80: 600 | I80: =2*C80 -> 1200 | J80: =2*E80 -> 1200
B81: Custo Total | C81: =C14 -> 127 | E81: =E53/2 -> 463.756 | I81: =2*C81 -> 254 | J81: =2*E81 -> 927.512
B82: Custo Alocado | C82: =C81*D69 -> 38.600928 | E82: =E81*D69 -> 140.956 | I82: =2*C82 -> 77.201856 | J82: =2*E82 -> 281.912
B83: Ganho de Capital | C83: =C80-C82 -> 561.39907 | E83: =E80-E82 -> 459.044 | I83: =2*C83 -> 1122.7981 | J83: =2*E83 -> 918.088
B85: IRPJ/CSLL (34%) | C85: =C83*34% -> 190.87568 | E85: =34%*E83 -> 156.07496 | G85: Δ (Economia) | I85: =2*C85 -> 381.75137 | J85: =2*E85 -> 312.14992 | K85: Δ (Economia)
B86: Ganho Liquido | C86: =C80-C85 -> 409.12432 | E86: =E80-E85 -> 443.92504 | G86: =E86-C86 -> 34.800724 | I86: =2*C86 -> 818.24863 | J86: =2*E86 -> 887.85008 | K86: =J86-I86 -> 69.601449
B87: Alíquota Efetiva (preço) | C87: =C85/C80 -> 0.31812614 | E87: =E85/E80 -> 0.26012493 | G87: =C87-E87 -> 0.058001207 | I87: =C87 -> 0.31812614 | J87: =E87 -> 0.26012493 | K87: =I87-J87 -> 0.058001207
B89: Custo Remanescente | C89: =C81-C82 -> 88.399072 | E89: =E81-E82 -> 322.8 | G89: =E89-C89 -> 234.40093 | I89: =2*C89 -> 176.79814 | J89: =2*E89 -> 645.6 | K89: =J89-I89 -> 468.80186

Sheet Segregação de Risco
G4: Segregação de risco
G5: 4 de setembro de 2026
B8: Segregação de Risco — Custo do Investimento das Holdings (CPC 15 × CPC 19)
B10: O que esta aba analisa
B11: Esta aba complementa a aba 'Cálculos da Operação'. Lá se apura o custo do investimento das Holdings (Savian e JVFJ) na Embracon após a incorporação da CNP e o imposto do cash-out, comparando o custo original (cenário A) com o custo incrementado pelo reflexo da incorporação (cenário B). Aqui respondemos a três perguntas que decorrem daquele resultado: (1) de que camadas é formado o custo incrementado e qual o risco fiscal de cada uma, no enquadramento da operação como combinação de negócios (CPC 15); (2) o que muda se a operação for enquadrada como operação em conjunto (CPC 19), em que as Holdings reconhecem 60% do valor justo de toda a JO e um imposto diferido 'carimbado' de 34%; e (3) quanto de imposto seria devido em uma venda futura dos 60%, pela Holding (PJ) ou pelas pessoas físicas (PF), em cada cenário. Os valores partem das premissas da aba 'Cálculos da Operação' (relacionadas abaixo) e estão em R$ milhões; as premissas específicas de cada bloco são indicadas no próprio bloco.
B13: Informações utilizadas (fonte: aba 'Cálculos da Operação', salvo indicação em contrário)
B14: Informação | C14: Valor | D14: Origem / observação
B15: Data-base dos balanços | C15: 30.06.2026 | D15: Balanços das companhias utilizados na aba 'Cálculos da Operação'
B16: Unidade | C16: R$ milhões
B17: Participação das Partes CNP na incorporação (relação de troca) | C17: ='Cálculos da Operação'!I15 -> 0.138 | D17: Ações novas emitidas pela Embracon às Partes CNP na incorporação
B18: Participação-alvo final das Partes CNP | C18: ='Cálculos da Operação'!I16 -> 0.4 | D18: Após o cash-out (compra de 26,2% das Holdings)
B19: Participação final das famílias (Savian + JVFJ) | C19: =1-C18 -> 0.6 | D19: Posição remanescente das Holdings, objeto da venda futura simulada no bloco 3
B20: Fração do investimento das Holdings alienada no cash-out | C20: ='Cálculos da Operação'!D69 -> 0.30394432 | D20: 13,1% vendidos ÷ 43,1% detidos por Holding — mesmo critério de alocação de custo da aba 'Cálculos da Operação'
B21: IRPJ/CSLL — ganho de capital PJ | C21: ='Cálculos da Operação'!I17 -> 0.34 | D21: Alíquota combinada aplicada às Holdings
B22: PL contábil da Embracon (antes da incorporação) | C22: ='Cálculos da Operação'!C19 -> 254 | D22: PL da Embracon; corresponde ao custo original das Holdings
B23: Custo original do investimento das Holdings (Savian + JVFJ) | C23: ='Cálculos da Operação'!F47 -> 254 | D23: Investimento original em Embracon: 127 de cada Holding
B24: PL contábil da CNP | C24: ='Cálculos da Operação'!C23 -> 800 | D24: Patrimônio líquido contábil da CNP incorporada
B25: Valor de mercado da CNP (valor pelo qual o acervo é incorporado no CPC 15 — PPA) | C25: ='Cálculos da Operação'!C24 -> 822 | D25: Valor de mercado adotado na aba 'Cálculos da Operação'
B26: Mais-valia da CNP (valor de mercado − PL contábil) | C26: =C25-C24 -> 22 | D26: Camada de avaliação a valor justo (AVJ) que o CPC 15 leva ao custo das Holdings via MEP
B28: 1) CPC 15 — Combinação de Negócios: de que é feito o custo do investimento das Holdings e onde está o risco
B30: Na combinação de negócios (CPC 15) a Embracon adquire o controle do negócio da CNP: o acervo da CNP entra pelo valor de mercado apurado em laudo (PPA) e o patrimônio da própria Embracon não é reavaliado. Nas Holdings, o investimento sobe pelo método de equivalência patrimonial (MEP): ao custo original soma-se o reflexo do acervo incorporado, deduzida a perda pela diluição de 13,8%. O quadro abre esse custo em camadas porque cada camada tem um risco fiscal diferente. O custo original é incontroverso. O reflexo do PL contábil da CNP depende da tese de que o resultado de equivalência é neutro para fins fiscais também na alienação futura (art. 33, §2º, do DL 1.598/77; precedente WTorre). O reflexo da mais-valia (valor de mercado acima do PL contábil) é a parcela mais exposta, por corresponder a uma avaliação a valor justo que nunca foi tributada. As colunas mostram o valor a 100% (PL da Embracon após a incorporação), a parcela das Holdings logo após a incorporação (86,2%) e a parcela remanescente após o cash-out (60%).
B32: 1.1 Composição do custo do investimento das Holdings, por camada
B33: Camada do custo | C33: PL Embracon pós-incorporação (100%) | D33: Holdings pós-incorporação (86,2%) | E33: Holdings após o cash-out (60%) | F33: Baixa no cash-out | G33: IR potencial (34%) sobre a camada | H33: Leitura de risco
B34: Custo original (PL contábil da Embracon) | C34: =C22 -> 254 | D34: =C23 -> 254 | E34: =D34*(1-$C$20) -> 176.79814 | F34: =E34-D34 -> -77.201856 | G34: – | H34: Incontroverso: custo histórico das ações; é o custo do cenário A da aba 'Cálculos da Operação'.
B35: (−) Perda por diluição de 13,8% sobre o custo original | C35: – | D35: =-D34*$C$17 -> -35.052 | E35: =D35*(1-$C$20) -> -24.398144 | F35: =E35-D35 -> 10.653856 | G35: =E35*$C$21 -> -8.2953689 | H35: Perda de MEP por variação de percentual: fiscalmente neutra (art. 33, §2º, DL 1.598/77); reduz o reflexo contábil (e o IR potencial da camada seguinte), não o custo fiscal original.
B36: Reflexo do PL contábil da CNP | C36: =C24 -> 800 | D36: =C36*(1-$C$17) -> 689.6 | E36: =C36*$C$19 -> 480 | F36: =E36-D36 -> -209.6 | G36: =E36*$C$21 -> 163.2 | H36: Risco limitado: reflexo MEP do PL incorporado a valor contábil; sustenta-se na tese de neutralidade do MEP (WTorre), com precedentes CARF 2024 em sentido contrário.
B37: Reflexo da mais-valia da CNP (AVJ do PPA) | C37: =C26 -> 22 | D37: =C37*(1-$C$17) -> 18.964 | E37: =C37*$C$19 -> 13.2 | F37: =E37-D37 -> -5.764 | G37: =E37*$C$21 -> 4.488 | H37: Camada mais exposta: valor de mercado acima do PL contábil, nunca tributado; é a parcela que o fisco tenderia a atacar primeiro.
B38: (=) Custo do investimento das Holdings | C38: =SUM(C34:C37) -> 1076 | D38: =SUM(D34:D37) -> 927.512 | E38: =SUM(E34:E37) -> 645.6 | F38: =SUM(F34:F37) -> -281.912 | G38: =SUM(G35:G37) -> 159.39263 | H38: Total das camadas: após a incorporação = custo incrementado; após o cash-out = custo remanescente do cenário B (aba 'Cálculos da Operação').
B39: Conferência com a aba 'Cálculos da Operação' (diferença; 'ok' = zero) | C39: – | D39: =ROUND(D38-'Cálculos da Operação'!E53,6) -> 0 | E39: =ROUND(E38-'Cálculos da Operação'!J89,6) -> 0 | F39: =ROUND(F38+'Cálculos da Operação'!J82,6) -> 0 | G39: – | H39: D = custo incrementado (E53) · E = custo remanescente do cenário B (J89) · F = custo alocado no cash-out (J82)
B41: 1.2 Leitura: quanto do custo remanescente é seguro e quanto está em discussão (após o cash-out)
B42: Parcela do custo após o cash-out | C42: Valor | D42: % do custo | E42: IR potencial (34%) | F42: Comentário
B43: Custo fiscal incontroverso (custo original remanescente = cenário A) | C43: =E34 -> 176.79814 | D43: =C43/$C$46 -> 0.2738509 | E43: – | F43: Custo aceito em qualquer leitura; é o cenário mais conservador da aba 'Cálculos da Operação'.
B44: Reflexo do PL contábil da CNP, líquido da perda por diluição (risco limitado) | C44: =E36+E35 -> 455.60186 | D44: =C44/$C$46 -> 0.705703 | E44: =C44*$C$21 -> 154.90463 | F44: Depende da tese de neutralidade do reflexo de MEP; o IR só seria devido se o fisco tributar o reflexo na alienação.
B45: Reflexo da mais-valia da CNP (maior exposição) | C45: =E37 -> 13.2 | D45: =C45/$C$46 -> 0.020446097 | E45: =C45*$C$21 -> 4.488 | F45: Parcela do PPA levada ao custo; com as premissas atuais é pequena, porque o valor de mercado da CNP está próximo do seu PL contábil.
B46: (=) Custo após o cash-out (cenário B) — incremento em discussão = linhas 2 + 3 | C46: =SUM(C43:C45) -> 645.6 | D46: =SUM(D43:D45) -> 1 | E46: =SUM(E44:E45) -> 159.39263 | F46: O incremento em discussão (C44 + C45) é exatamente a diferença de custo remanescente entre os cenários B e A da aba 'Cálculos da Operação'.
B47: Conferência: incremento em discussão − Δ custo remanescente da aba 'Cálculos da Operação' (K89) | C47: =ROUND(C44+C45-'Cálculos da Operação'!K89,6) -> 0
B49: 2) CPC 19 — Joint Operation: reconhecimento de 60% do valor justo da JO e imposto diferido 'carimbado'
B51: Na operação em conjunto (CPC 19), leitura sustentada pela Deloitte a partir dos vetos qualificados da CNP, as Holdings deixam de avaliar o investimento pelo MEP e passam a reconhecer diretamente a sua parcela (60%) dos ativos e passivos da JO — Embracon e CNP — a valor justo. Isso inclui o valor justo da própria Embracon, que no CPC 15 não é reavaliada. O ganho de avaliação a valor justo (AVJ) não é tributado no reconhecimento, desde que controlado em subconta (arts. 13 e 14 da Lei 12.973/14), mas fica 'carimbado': o IRPJ/CSLL de 34% sobre o AVJ é devido quando o investimento for realizado (venda), qualquer que seja o preço e independentemente de quem venda. O bloco usa como valor justo da Embracon o enterprise value do Acordo de Investimento (premissa editável abaixo) e, para a CNP, o valor de mercado já adotado na aba 'Cálculos da Operação'.
B53: 2.1 Premissa adicional deste bloco
B54: Valor justo da Embracon — enterprise value do Acordo de Investimento (data-base 31.12.2024) | C54: 5133 | D54: Premissa editável. No CPC 15 a Embracon não é reavaliada; no CPC 19 o seu valor justo entra integralmente no investimento das Holdings.
B56: 2.2 Investimento das Holdings na JO (após o cash-out, 60%)
B57: Componente | C57: 100% da JO | D57: 60% (Holdings) | E57: Leitura
B58: Valor justo da Embracon | C58: =C54 -> 5133 | D58: =C58*$C$19 -> 3079.8 | E58: Parcela que não existe no CPC 15: a Embracon passa a ser reavaliada.
B59: Valor justo da CNP (= valor de mercado) | C59: =C25 -> 822 | D59: =C59*$C$19 -> 493.2 | E59: Mesmo valor incorporado no CPC 15.
B60: (=) Valor justo total da JO — custo do investimento das Holdings no CPC 19 | C60: =C58+C59 -> 5955 | D60: =D58+D59 -> 3573 | E60: Investimento reconhecido pelas Holdings: 60% do valor justo de Embracon + CNP.
B61: (−) Base contábil (PL da Embracon + PL contábil da CNP) | C61: =C22+C24 -> 1054 | D61: =C61*$C$19 -> 632.4 | E61: Coincide com o custo do CPC 15 sem a camada da mais-valia (bloco 1: custo original + diluição + reflexo do PL contábil).
B62: (=) Ganho de AVJ com tributação diferida (subconta — arts. 13 e 14, Lei 12.973/14) | C62: =C60-C61 -> 4901 | D62: =D60-D61 -> 2940.6 | E62: Ganho reconhecido no resultado das Holdings e neutralizado fiscalmente apenas enquanto controlado em subconta.
B63: Passivo fiscal diferido 'carimbado' (34% × AVJ) | C63: =C62*$C$21 -> 1666.34 | D63: =D62*$C$21 -> 999.804 | E63: Devido na realização do investimento (venda), independentemente do preço; é o piso de imposto do CPC 19 nos blocos 3 e 5.
B65: 2.3 Custo do investimento das Holdings após o cash-out — CPC 15 × CPC 19
B66: Cenário | C66: Custo (60%) | D66: Δ vs. CPC 15 | E66: Leitura
B67: CPC 15 — custo incrementado remanescente (bloco 1) | C67: =E38 -> 645.6 | D67: – | E67: Custo formado pelo custo original mais o reflexo da CNP a valor de mercado; sem passivo fiscal diferido.
B68: CPC 19 — 60% do valor justo da JO (bloco 2) | C68: =D60 -> 3573 | D68: =C68-C67 -> 2927.4 | E68: A diferença é o AVJ de toda a JO (60%) menos a mais-valia da CNP que o CPC 15 já leva ao custo; sobre o AVJ há IR diferido de 34%.
B70: 3) Venda futura dos 60% — IRPJ/CSLL em cada cenário, pela Holding (PJ) ou pelas pessoas físicas (PF)
B72: Simulamos a venda dos 60% remanescentes em três preços — abaixo, igual e acima do valor justo (60% do valor justo da JO). No CPC 15, o imposto incide sobre a diferença entre o preço e o custo fiscal apurado no bloco 1 (custo incrementado remanescente). No CPC 19, o imposto diferido de 34% sobre o AVJ é devido de qualquer forma e funciona como piso; se o preço superar o valor justo, o excedente também é tributado. Na venda pelas pessoas físicas (após 'subir' as ações das Holdings para as PFs), aplica-se a alíquota simplificada de 22,5% sobre o ganho; porém o custo das PFs é o custo das quotas das Holdings, muito inferior ao custo da Holding, e no CPC 19 o imposto carimbado permanece na Holding mesmo que a venda seja feita pela PF.
B74: 3.1 Premissas deste bloco
B75: Preço de venda abaixo do valor justo | C75: 1000 | D75: Premissa editável (cenário i do material SF).
B76: Preço de venda igual ao valor justo (60% do valor justo da JO) | C76: =D60 -> 3573 | D76: Calculado a partir do bloco 2.
B77: Preço de venda acima do valor justo | C77: 5000 | D77: Premissa editável (cenário iii do material SF).
B78: Alíquota de IR da pessoa física — ganho de capital (simplificada) | C78: 0.225 | D78: Alíquota progressiva de 15% a 22,5%; adotada a máxima, por simplificação.
B79: Custo das quotas das Holdings nas pessoas físicas | C79: 18 | D79: Premissa ilustrativa do exercício da MLA, a confirmar com o custo real das quotas.
B81: 3.2 Imposto na venda dos 60% (IRPJ/CSLL de 34% na Holding; IR de 22,5% na PF)
B82: Cenário de preço | C82: Preço de venda | D82: CPC 15 — venda pela Holding | E82: CPC 15 — venda pela PF | F82: CPC 19 — venda pela Holding | G82: CPC 19 — venda pela PF | H82: Δ CPC 19 − CPC 15 (venda pela Holding)
B83: Abaixo do valor justo | C83: =C75 -> 1000 | D83: =(C83-$E$38)*$C$21 -> 120.496 | E83: =(C83-$C$79)*$C$78 -> 220.95 | F83: =MAX($D$63,(C83-$D$61)*$C$21) -> 999.804 | G83: =$D$63+MAX(0,C83-$D$60)*$C$78 -> 999.804 | H83: =F83-D83 -> 879.308
B84: Igual ao valor justo | C84: =C76 -> 3573 | D84: =(C84-$E$38)*$C$21 -> 995.316 | E84: =(C84-$C$79)*$C$78 -> 799.875 | F84: =MAX($D$63,(C84-$D$61)*$C$21) -> 999.804 | G84: =$D$63+MAX(0,C84-$D$60)*$C$78 -> 999.804 | H84: =F84-D84 -> 4.488
B85: Acima do valor justo | C85: =C77 -> 5000 | D85: =(C85-$E$38)*$C$21 -> 1480.496 | E85: =(C85-$C$79)*$C$78 -> 1120.95 | F85: =MAX($D$63,(C85-$D$61)*$C$21) -> 1484.984 | G85: =$D$63+MAX(0,C85-$D$60)*$C$78 -> 1320.879 | H85: =F85-D85 -> 4.488
B86: Fórmulas: CPC 15 PJ = (preço − custo do bloco 1) × 34% · CPC 15 PF = (preço − custo das quotas) × 22,5% · CPC 19 PJ = maior entre o imposto carimbado e (preço − base contábil) × 34% · CPC 19 PF = imposto carimbado na Holding + 22,5% sobre o excedente ao valor justo.
B87: Leitura: em preços iguais ou superiores ao valor justo, a diferença entre os regimes na venda pela Holding é pequena e corresponde a 34% da mais-valia da CNP — a única camada que o CPC 15 leva ao custo e o CPC 19 tributa. Abaixo do valor justo, o CPC 19 é substancialmente mais oneroso, porque o imposto diferido não diminui com o preço. A venda pela PF só é vantajosa no CPC 15, e apenas a partir de preços em que a alíquota menor compensa o custo menor das quotas; no CPC 19 ela não elimina o imposto carimbado, que permanece na Holding.
B89: 3.3 Por que o imposto diferido do CPC 19 funciona como piso — venda abaixo do valor justo
B90: Movimento na Holding (CPC 19) | C90: Valor | D90: Comentário
B91: Baixa do investimento (60% do valor justo da JO) | C91: =-D60 -> -3573 | D91: Valor contábil do investimento reconhecido no CPC 19.
B92: Preço recebido | C92: =C75 -> 1000
B93: (=) Resultado contábil da venda | C93: =C91+C92 -> -2573 | D93: Prejuízo contábil, porque o preço é inferior ao valor justo reconhecido.
B94: IR diferido 'carimbado' devido na realização | C94: =D63 -> 999.804 | D94: Devido integralmente: a subconta é baixada com a venda.
B95: Crédito teórico sobre a perda (34%) | C95: =C93*$C$21 -> -874.82 | D95: No lucro presumido a perda não é aproveitável; no lucro real, a compensação é limitada à trava de 30% e depende de lucros futuros.
B96: Carga líquida teórica (se a perda fosse integralmente aproveitada) | C96: =C94+C95 -> 124.984 | D96: Coincide com o RISCO 2 do bloco 4 (mesma base contábil).
B97: Carga adotada nos quadros (piso = imposto carimbado) | C97: =F83 -> 999.804 | D97: Leitura conservadora adotada no material: o imposto carimbado é pago e a perda não gera economia.
B99: 4) Sensibilidade do CPC 15 — e se o fisco não aceitar as camadas do custo?
B101: O quadro testa o cenário CPC 15 sob duas hipóteses adversas. RISCO 2: o fisco não aceita a camada da mais-valia — o custo fiscal recua para a base contábil (custo original + reflexo do PL contábil da CNP). RISCO 1: o fisco não aceita nenhuma camada do reflexo — resta apenas o custo original remanescente (cenário A da aba 'Cálculos da Operação'). Cada degrau de risco tem valor fixo, igual a 34% da camada negada, independentemente do preço de venda.
B103: Cenário de preço | C103: Preço de venda | D103: CPC 15 — custo integral (bloco 1) | E103: RISCO 2 — fisco nega a mais-valia | F103: RISCO 1 — fisco nega todo o reflexo | G103: Δ RISCO 2 = 34% × mais-valia | H103: Δ RISCO 1 = 34% × incremento em discussão
B104: Custo fiscal considerado em cada hipótese | C104: – | D104: =E38 -> 645.6 | E104: =E38-E37 -> 632.4 | F104: =E34 -> 176.79814 | G104: =D104-E104 -> 13.2 | H104: =D104-F104 -> 468.80186
B105: Abaixo do valor justo | C105: =C83 -> 1000 | D105: =(C105-$D$104)*$C$21 -> 120.496 | E105: =(C105-$E$104)*$C$21 -> 124.984 | F105: =(C105-$F$104)*$C$21 -> 279.88863 | G105: =E105-D105 -> 4.488 | H105: =F105-D105 -> 159.39263
B106: Igual ao valor justo | C106: =C84 -> 3573 | D106: =(C106-$D$104)*$C$21 -> 995.316 | E106: =(C106-$E$104)*$C$21 -> 999.804 | F106: =(C106-$F$104)*$C$21 -> 1154.7086 | G106: =E106-D106 -> 4.488 | H106: =F106-D106 -> 159.39263
B107: Acima do valor justo | C107: =C85 -> 5000 | D107: =(C107-$D$104)*$C$21 -> 1480.496 | E107: =(C107-$E$104)*$C$21 -> 1484.984 | F107: =(C107-$F$104)*$C$21 -> 1639.8886 | G107: =E107-D107 -> 4.488 | H107: =F107-D107 -> 159.39263
B108: Leitura: o RISCO 2 coincide com o CPC 19 nas vendas ao valor justo ou acima (mesma base contábil); abaixo do valor justo o CPC 19 continua pior, pelo piso do imposto carimbado. Já o RISCO 1 supera o CPC 19 em qualquer preço a partir do valor justo: se a tese de neutralidade do reflexo do PL contábil da CNP fosse integralmente afastada, o CPC 15 deixaria de ser o cenário mais favorável na venda futura — daí a importância de documentar a tese e o laudo (PPA).
B110: 5) Conclusão executiva — CPC 15 × CPC 19
B112: Ponto de comparação | C112: CPC 15 | D112: CPC 19 | E112: Δ (CPC 19 − CPC 15) | F112: Leitura
B113: Custo do investimento das Holdings após o cash-out | C113: =E38 -> 645.6 | D113: =D60 -> 3573 | E113: =D113-C113 -> 2927.4 | F113: No CPC 19 o custo inclui 60% do AVJ de toda a JO; no CPC 15 apenas o reflexo da CNP a valor de mercado.
B114: Parcela do custo com IR diferido (CPC 19) ou em discussão com o fisco (CPC 15) | C114: =C44+C45 -> 468.80186 | D114: =D62 -> 2940.6 | E114: =D114-C114 -> 2471.7981 | F114: CPC 15: reflexo cuja neutralidade depende de tese; CPC 19: AVJ carimbado, sem discussão.
B115: IR potencial sobre essa parcela (34%) | C115: =E46 -> 159.39263 | D115: =D63 -> 999.804 | E115: =D115-C115 -> 840.41137 | F115: CPC 15: devido só se o fisco negar o custo e prevalecer; CPC 19: devido na venda, qualquer que seja o preço.
B116: IR na venda pela Holding — preço abaixo do valor justo | C116: =D83 -> 120.496 | D116: =F83 -> 999.804 | E116: =D116-C116 -> 879.308 | F116: O piso do imposto carimbado torna o CPC 19 muito mais oneroso em vendas abaixo do valor justo.
B117: IR na venda pela Holding — preço igual ao valor justo | C117: =D84 -> 995.316 | D117: =F84 -> 999.804 | E117: =D117-C117 -> 4.488 | F117: Diferença = 34% da mais-valia da CNP: nos preços a partir do valor justo os regimes se aproximam.
B118: IR na venda pela Holding — preço acima do valor justo | C118: =D85 -> 1480.496 | D118: =F85 -> 1484.984 | E118: =D118-C118 -> 4.488 | F118: Mesma diferença fixa; o excedente ao valor justo é tributado a 34% nos dois regimes.
B119: IR na venda pelas pessoas físicas — preço igual ao valor justo | C119: =E84 -> 799.875 | D119: =G84 -> 999.804 | E119: =D119-C119 -> 199.929 | F119: Só o CPC 15 permite capturar a alíquota de 22,5%; no CPC 19 o imposto carimbado fica na Holding.
B120: CPC 15 em cenário adverso (RISCO 1) × CPC 19 — preço igual ao valor justo | C120: =F106 -> 1154.7086 | D120: =F84 -> 999.804 | E120: =D120-C120 -> -154.90463 | F120: Se a tese de neutralidade do reflexo for integralmente afastada, o CPC 15 passa a ser mais oneroso que o CPC 19.
B122: • CPC 15 é o cenário mais favorável às Holdings: o custo do investimento incorpora o reflexo da incorporação sem registro de passivo fiscal diferido, o imposto na venda futura acompanha o preço e existe a alternativa de venda pelas pessoas físicas à alíquota de 22,5%. O risco concentra-se na neutralidade do reflexo do PL contábil da CNP (bloco 1); com as premissas atuais a mais-valia é pequena e o imposto potencial sobre ela é residual.
B123: • CPC 19 elimina a discussão sobre o custo, mas ao preço de reconhecer ganho de AVJ sobre toda a JO — inclusive a Embracon, que no CPC 15 não é reavaliada — com IRPJ/CSLL de 34% carimbado e devido na venda em qualquer cenário de preço, sem a alternativa da PF. Além disso, o valor patrimonial das Holdings sobe ao valor justo, com impacto direto na base de cálculo do ITCMD (tema não tratado neste material).
B124: • Na venda ao valor justo ou acima, a carga dos dois regimes é próxima (diferença = 34% da mais-valia da CNP); abaixo do valor justo, o CPC 19 é substancialmente mais oneroso. Se a tese de neutralidade do reflexo fosse integralmente afastada (RISCO 1), o CPC 15 passaria a ser mais oneroso que o CPC 19 nas vendas a partir do valor justo — daí a importância de documentar a tese e o laudo de avaliação (PPA).
B126: Ressalvas: valores ilustrativos em R$ milhões, data-base 30.06.2026, com as premissas da aba 'Cálculos da Operação' e valor justo da Embracon pelo EV do Acordo de Investimento. As Holdings estão no lucro presumido; na venda futura, a carga efetiva na PJ poderia ser reduzida com a opção pelo lucro real e a existência de prejuízos compensáveis. O custo das quotas nas PFs é premissa ilustrativa a confirmar. O material não avalia o ITCMD nem o cash-out no CPC 19, tratado na aba 'Cálculos da Operação' com o custo original (cenário A) e o incrementado (cenário B).

Sheet Dourada C. e A. SA
K2: Base das informações
B3: DOURADA COMERCIAL E AGROPECUARIA S/A | C3: Lucro Real | G3: 45627 | I3: Prejuízo Fiscal IRPJ | J3: 956469.6 | K3: -Excel LALUR 2024
B4: Ativos | D4: =SUM(D5+D11) -> 10218400 | E4: Passivos | G4: =SUM(G5+G10+G13) -> 10218400 | I4: Prejuízo Fiscal CSLL | J4: 956469.6 | K4: -Excel LALUR 2024
B5: Ativos circulantes | D5: =SUM(D6:D10) -> 1964054.2 | E5: Passivos circulantes | G5: =SUM(G6:G9) -> 132218.99 | J5: =SUM(J3+J4) -> 1912939.2
C6: Caixa e equivalentes de caixa | D6: 2 | F6: Empréstimos e financiamentos | G6: 0 | I6: Provisão p/ devedores duvidosos | J6: 34739.57 | K6: -Excel LALUR 2024
C7: Contas a receber | D7: 1072152.6 | F7: Fornecedores | G7: 102122.6
C8: Outras contas a receber (adiantamentos) | D8: 22442.37 | F8: Provisões trab/tribut | G8: 30096.39
C9: Títulos e valores mobiliários | D9: 326886.99 | F9: Adiantamento de clientes | G9: 0
C10: Impostos a compensar | D10: 542570.31 | E10: Passivos não circulantes | G10: =SUM(G11:G12) -> 32527.28
B11: Ativo Permanente | D11: =D13 -> 8254345.4 | F11: Dividendos | G11: 32527.28
C12: Investimentos | D12: 0 | F12: Empréstimos e financiamentos | G12: 0
C13: Imobilizado | D13: 8254345.4 | E13: Patrimônio líquido | G13: =SUM(G14:G17) -> 10053653
F14: Capital subscrito e integralizado | G14: 14139130
F15: Reserva de reavaliação | G15: 4562148.4
F16: Reserva de lucros (reserva legal) | G16: 48664.65
F17: Lucros/Prejuízos acumulados | G17: -8696289.6
B21: Incentivos Fiscais | C21: Base de Cálculo do Incentivo | D21: Limite de Dedução Individual | E21: Embasamento Legal
B22: Programa de Alimentação ao Trabalhador - PAT | C22: objetivo de melhorar as condições nutricionais e de qualidade de vida dos trabalhadores | D22: 4% do IRPJ devido ANTES ADCIONAL 10% | E22: Artigos 491 a 493, 504 a 507, 581 a 587 do RIR/99
B23: Doações aos Fundos dos Direitos da Criança e do Adolescente | C23: Doações efetivamente realizadas | D23: 1% do IRPJ devido ANTES ADICIONAL 10% | E23: Art. 591 do RIR/99
B24: Atividade Audiovisual | C24: Valores aplicados na aquisição de certificados de investimentos em projetos aprovados pelo Ministério da Cultura | D24: 3% do IRPJ devido ANTES ADICIONAL 10% | E24: Artigos 475 478, 484 a 488 do RIR/99
B25: LEI DE INCENTIVO A CULTURAL - ROUANET | C25: É a lei que institui o Programa Nacional de Apoio à Cultura - PRONAC | D25: 4% do IRPJ devido ANTES ADICIONAL 10% | E25: Base Legal: Lei 8.313/1991; Lei 9.874/1999; Decreto 3.000/1999; Instrução Normativa-SRF 267/2002 e Instrução Normativa-SRF 390/2004.
B26: FUNDO MUNICIPAL DO IDOSO - FMI | C26: doações efetuadas aos respectivos fundos municipais, estaduais e nacional. | D26: 1% do IRPJ devido ANTES ADCIONAL 10% | E26: LEI 12.213
B27: LEI DE INCENTIVO AO ESPORTE - LIE | C27: Objetiva principalmente incentivar o esporte de um modo geral. | D27: 1% do IRPJ devido ANTES ADICIONAL 10% | E27: LEI 11.438

Sheet Embracon Franchising
B3: EMBRACON FRANCHISING LTDA | C3: Lucro Presumido | G3: 45627 | L3: Excel: LALUR
B4: Ativos | D4: =SUM(D5+D9) -> 1167425.5 | E4: Passivos | G4: =G5+G7 -> 1167425.5
B5: Ativos circulantes | D5: =SUM(D6:D8) -> 383408.33 | E5: Passivos circulantes | G5: =G6 -> 17724.87
C6: Caixa e equivalentes de caixa | D6: 1 | F6: Fiscais e previdenciários | G6: 17724.87
C7: Titulos e Valores Mobiliários | D7: 317739.29 | E7: Patrimônio líquido | G7: =SUM(G8:G10) -> 1149700.6
C8: Outros créditos | D8: 65668.04 | F8: Capital subscrito e integralizado | G8: 1150000
B9: Ativo não circulante | D9: =D10 -> 784017.14 | F9: Capital a integralizar | G9: -200000
C10: Realizável a longo prazo - outros investimentos | D10: 784017.14 | F10: Reseva de Lucros | G10: 199700.6

Sheet Embrafisa Consul.
B3: EMBRAFISA CONSUL. EMPRE. CORRE. DE SEGU. E EMPREEND. IMOB. LTDA | C3: Lucro Presumido | G3: 45627 | H3: Balanço | L3: Excel: LALUR
B4: Ativos | D4: =SUM(D5+D12) -> 1.2237116e+08 | E4: Passivos | G4: =SUM(G5+G10) -> 1.2237116e+08
B5: Ativos circulantes | D5: =SUM(D6:D11) -> 14442337 | E5: Passivos circulantes | G5: =SUM(G6:G9) -> 21461592
C6: Caixa e equivalentes | D6: 2437109.3 | F6: Obrigações trib. | G6: 2494169
C7: clientes | D7: 7001150.1 | F7: Obrigações Trab. | G7: 558759.63
C8: adiantamentos | D8: 1273637.1 | F8: Contas a pagar | G8: 17920182
C9: Estoques | D9: 3718389.1 | F9: Previsão de adiantamento de clientes | G9: 488481.84
C10: Impostos a compensar | D10: 1006.72 | E10: Patrimônio líquido | G10: =SUM(G11:G12) -> 1.0090957e+08
C11: Ações Judiciais | D11: 11044.49 | F11: Capital subscrito e integralizado | G11: 86545880
B12: Ativo não circulante | D12: =SUM(D13:D14) -> 1.0792883e+08 | F12: Reserva de lucros | G12: 14363691
C13: Investimentos | D13: 46794804
C14: Imobilizado | D14: 61134022

Sheet GSJ
B3: COMPANHIA GSJ DE PART. | C3: Lucro Presumido | G3: 45627 | L3: Excel: LALUR
B4: Ativos | D4: =SUM(D5+D9) -> 1.0937994e+08 | E4: Passivos | G4: =SUM(G5+G9) -> 1.0937994e+08 | H4: GSJ Balanço
B5: Ativos circulantes | D5: =SUM(D6:D8) -> 820384.91 | E5: Passivos circulantes | G5: =SUM(G6:G8) -> 919578.08
C6: Caixa e equivalente | D6: 7 | F6: Fiscais e Previdenciarias | G6: 6731.94
C7: Titulos e valores mobiliarios | D7: 501276.83 | F7: Diversas | G7: 360471.48
C8: Outros creditos | D8: 319101.08 | F8: Dividendos a pagar | G8: 552374.66
B9: Ativo não circulante | D9: =SUM(D10:D12) -> 1.0855956e+08 | E9: Patrimônio líquido | G9: =SUM(G10:G14) -> 1.0846036e+08
C10: Participação societárias | D10: 64315927 | F10: Capital subscrito e integralizado | G10: 79875998
C11: Outros investimentos | D11: 21372770 | F11: Capital a integralizar | G11: -2603500
C12: Imobilizado | D12: 22870861 | F12: Reserva legal | G12: 1800035.9
F13: reserva de lucros | G13: 7330593.3
F14: Lucros/Prejuizos acumulados | G14: 22057238
