Workbook

Sheet Premissas
E1: Projeto Another House — Exercício da Incorporação sob CPC 15
E2: Hipótese A: custo original ("magrinho") · Hipótese B: custo incrementado ("gordinho")
B4: Base: draft MLA, aba "base 30 06 26com dividendos" · valores em R$ milhões · células AMARELAS = premissas editáveis; o restante é fórmula.
B6: PREMISSAS GERAIS
B7: Data-base dos balanços | C7: 30.06.2026
B8: Participação das Partes CNP na incorporação (relação de troca) | C8: 0.138 | D8: Draft E71
B9: Participação final das Partes CNP (pós cash out) | C9: 0.4 | D9: Draft E87
B10: IRPJ/CSLL sobre ganho de capital | C10: 0.34 | D10: Draft I96
B11: Dividendos declarados pela Embracon antes da incorporação | C11: 120 | D11: Draft L23/L31 — reduz o PL da Embracon a 239,5
B12: Preço do cash out — por holding | C12: 600 | D12: Draft G97 (total 1.200 nas duas holdings)
B14: SEGREGAÇÃO DO CUSTO — PROPORÇÃO DO EXEMPLO DELOITTE
B15: Valor justo do PL da CNP (exemplo DTT) | C15: 866 | D15: Draft N86
B16: Mais-valia contida no exemplo (MV) | C16: 300 | D16: Draft O86
B17: % AVJ implícito no PL da CNP (MV ÷ VJ) | C17: =C16/C15 -> 0.34642032 | D17: Aplicado ao PL contábil da CNP para segregar a camada de maior risco
B18: % contábil (sem AVJ) | C18: =1-C17 -> 0.65357968

Sheet Contabilização
B1: Contabilização — do balanço-base à alienação futura
B3: 0. BALANÇOS-BASE 30.06.2026 (R$ MILHÕES)
C4: SAVIAN | D4: JVFJ | E4: EMBRACON | F4: CNP
B5: Ativos totais | C5: =C11 -> 119.744 | D5: =D11 -> 119.744 | E5: 26138.03 | F5: 17611.435
B6: Passivos totais | C6: 0 | D6: 0 | E6: 25898.882 | F6: 16771.856
B7: Patrimônio líquido | C7: =E7/2 -> 119.744 | D7: =E7/2 -> 119.744 | E7: =SUM(E8:E10) -> 239.488 | F7: =SUM(F8:F10) -> 838.735
B8: Capital | E8: 85 | F8: 519
B9: Reservas | E9: 274.488 | F9: 319.735
B10: (−) Dividendos declarados | E10: =-Premissas!$C$11 -> -120
B11: Investimento na Embracon (= 50% do PL) | C11: =E7/2 -> 119.744 | D11: =E7/2 -> 119.744
B12: PL combinado (Embracon + CNP) | C12: =E7+F7 -> 1078.223
B13: Savian e JVFJ: ativo único = investimento na Embracon. CNP: PL = Capital 519 + Reservas 319,7 (draft).
B15: 1. PRÉ-INCORPORAÇÃO — PARTICIPAÇÕES E CUSTO
C16: SAVIAN | D16: JVFJ | E16: CNP | F16: TOTAL
B17: Participação na Embracon | C17: 0.5 | D17: 0.5 | E17: 0 | F17: =SUM(C17:E17) -> 1
B18: Custo do investimento | C18: =C11 -> 119.744 | D18: =D11 -> 119.744 | F18: =C18+D18 -> 239.488
B20: 2. INCORPORAÇÃO DA CNP — RELAÇÃO DE TROCA 13,8%
C21: SAVIAN | D21: JVFJ | E21: CNP | F21: TOTAL
B22: Participação após a incorporação | C22: =C17*(1-Premissas!$C$8) -> 0.431 | D22: =D17*(1-Premissas!$C$8) -> 0.431 | E22: =Premissas!$C$8 -> 0.138 | F22: =SUM(C22:E22) -> 1
B24: Reflexo nas holdings | C24: POR HOLDING | D24: TOTAL (2 HOLDINGS)
B25: Investimento anterior | C25: =C11 -> 119.744 | D25: =C25*2 -> 239.488
B26: (+) Incorporação base (PL da CNP ÷ 2) | C26: =F7/2 -> 419.3675 | D26: =C26*2 -> 838.735
B27: (−) Diluição de 13,8% sobre (investimento + base) | C27: =-(C25+C26)*Premissas!$C$8 -> -74.397387 | D27: =C27*2 -> -148.79477
B28: (=) Parcela incorporada | C28: =C26+C27 -> 344.97011 | D28: =C28*2 -> 689.94023
B29: (=) Custo incrementado — Hipótese B ("gordinho") | C29: =C25+C28 -> 464.71411 | D29: =C29*2 -> 929.42823
B30: Check: 43,1% × PL combinado − custo incrementado | C30: =C22*C12-C29 -> 0
B32: Segregação do custo (camadas de risco) | C32: PL COMBINADO | D32: × 86,2% | E32: Δ (2 HOLDINGS)
B33: 1. Investimento antigo (PL Embracon) — perda de diluição | C33: =E7 -> 239.488 | D33: =C33*(1-Premissas!$C$8) -> 206.43866 | E33: =D33-C33 -> -33.049344
B34: 2. Reflexo do PL contábil da CNP (menor risco) | C34: =F7*Premissas!$C$18 -> 548.18015 | D34: =C34*(1-Premissas!$C$8) -> 472.53129 | E34: =D34 -> 472.53129
B35: 3. Reflexo da parcela AVJ implícita (maior risco) | C35: =F7*Premissas!$C$17 -> 290.55485 | D35: =C35*(1-Premissas!$C$8) -> 250.45828 | E35: =D35 -> 250.45828
B36: Total | C36: =SUM(C33:C35) -> 1078.223 | D36: =SUM(D33:D35) -> 929.42823 | E36: =SUM(E33:E35) -> 689.94023
B38: CONCLUSÃO DA INCORPORAÇÃO
B39: Custo original — Hipótese A (por holding) | C39: =C11 -> 119.744
B40: Custo incrementado — Hipótese B (por holding) | C40: =C29 -> 464.71411
B41: Parcela incorporada — total (2 holdings) | C41: =D28 -> 689.94023
B43: 3. SITUAÇÃO APÓS A INCORPORAÇÃO — O ACERVO VERTIDO (CINDIDO) E OS BALANÇOS
B44: 3.1 Acervo líquido da CNP vertido à Embracon (linha a linha) | C44: VALOR
B45: Ativos — Circulante + realizável LP | C45: 945.234
B46: Ativos — CPC 47 (despesas/comissões diferidas) | C46: 216.353
B47: Ativos — Permanente | C47: 138.693
B48: Ativos — Compensação (grupos de consórcio) | C48: 16311.155
B49: Total de ativos vertidos | C49: =SUM(C45:C48) -> 17611.435
B50: (−) Passivos — Circulante | C50: -232.757
B51: (−) Passivos — CPC 47 (receitas diferidas) | C51: -227.944
B52: (−) Passivos — Compensação (grupos de consórcio) | C52: =-C48 -> -16311.155
B53: Total de passivos assumidos | C53: =SUM(C50:C52) -> -16771.856
B54: ACERVO LÍQUIDO VERTIDO | C54: =C49+C53 -> 839.579
B55: Check: acervo líquido − PL contábil da CNP (diferença da base do draft, a conciliar) | C55: =C54-F7 -> 0.844
B57: 3.2 Embracon combinada — balanço após a incorporação | C57: EMBRACON ANTES | D57: ACERVO VERTIDO (CNP) | E57: EMBRACON APÓS
B58: Ativo — Circulante | C58: 328.578 | D58: =C45 -> 945.234 | E58: =C58+D58 -> 1273.812
B59: Ativo — CPC 47 (despesas/comissões diferidas) | C59: 1937.402 | D59: =C46 -> 216.353 | E59: =C59+D59 -> 2153.755
B60: Ativo — Permanente | C60: 57.986 | D60: =C47 -> 138.693 | E60: =C60+D60 -> 196.679
B61: Ativo — Compensação | C61: 23814.064 | D61: =C48 -> 16311.155 | E61: =C61+D61 -> 40125.219
B62: Total de ativos | C62: =SUM(C58:C61) -> 26138.03 | D62: =SUM(D58:D61) -> 17611.435 | E62: =C62+D62 -> 43749.465
B63: Passivo — Circulante | C63: 420.06 | D63: =-C50 -> 232.757 | E63: =C63+D63 -> 652.817
B64: Passivo — CPC 47 (receitas diferidas) | C64: 1544.758 | D64: =-C51 -> 227.944 | E64: =C64+D64 -> 1772.702
B65: Passivo — Dividendos a pagar | C65: =Premissas!$C$11 -> 120 | E65: =C65 -> 120
B66: Passivo — Compensação | C66: =C61 -> 23814.064 | D66: =D61 -> 16311.155 | E66: =C66+D66 -> 40125.219
B67: Total de passivos | C67: =SUM(C63:C66) -> 25898.882 | D67: =SUM(D63:D66) -> 16771.856 | E67: =C67+D67 -> 42670.738
B68: PL — Capital social | C68: =E8 -> 85 | D68: =F8 -> 519 | E68: =C68+D68 -> 604
B69: PL — Reservas | C69: =E9 -> 274.488 | D69: =F9 -> 319.735 | E69: =C69+D69 -> 594.223
B70: PL — (−) Dividendos declarados | C70: =E10 -> -120 | E70: =C70 -> -120
B71: Patrimônio líquido após | C71: =SUM(C68:C70) -> 239.488 | D71: =SUM(D68:D70) -> 838.735 | E71: =C71+D71 -> 1078.223
B72: Check (Ativos − Passivos − PL): diferenças da base do draft, a conciliar | C72: =C62-C67-C71 -> -0.34 | D72: =D62-D67-D71 -> 0.844 | E72: =E62-E67-E71 -> 0.504
B74: 3.3 Balanço das holdings após (abertura do investimento) | C74: SAVIAN | D74: JVFJ
B75: Inv. Embracon — custo antigo | C75: =C11 -> 119.744 | D75: =D11 -> 119.744
B76: (+) Incorporação base (acervo ÷ 2, a valor contábil) | C76: =C26 -> 419.3675 | D76: =C26 -> 419.3675
B77: (−) Diluição de 13,8% | C77: =C27 -> -74.397387 | D77: =C27 -> -74.397387
B78: (=) Investimento e PL da holding após | C78: =SUM(C75:C77) -> 464.71411 | D78: =SUM(D75:D77) -> 464.71411
B79: Check: 43,1% × PL combinado após − investimento da holding | C79: =C22*E71-C78 -> 0
B81: 3.4 Prova da somatória (como no draft) | C81: VALOR
B82: PL combinado após a incorporação | C82: =E71 -> 1078.223
B83: Participação das Partes CNP (13,8%) | C83: =E71*Premissas!$C$8 -> 148.79477
B84: Participação Savian + JVFJ (86,2%) | C84: =E71*(1-Premissas!$C$8) -> 929.42823
B85: por holding (÷ 2) | C85: =C84/2 -> 464.71411
B86: Diluição individual (participação CNP ÷ 2) | C86: =C83/2 -> 74.397387
B87: Check: inv. anterior (239,5) + parcela incorporada (690,0) − participação S+J | C87: =E7+D28-C84 -> 0
B88: CNP Consórcio: extinta na incorporação (balanço zerado). O acervo entra a valor contábil; o risco fiscal está no reflexo que ele gera nas holdings — segregado em 3 camadas na seção 2 (a camada AVJ é a de maior risco).
B90: 4. CASH OUT — VENDA DE 26,2% À CNP (600 POR HOLDING)
C91: SAVIAN | D91: JVFJ | E91: CNP | F91: TOTAL
B92: Participação após a incorporação | C92: =C22 -> 0.431 | D92: =D22 -> 0.431 | E92: =E22 -> 0.138 | F92: =SUM(C92:E92) -> 1
B93: Venda / compra | C93: =-(Premissas!$C$9-Premissas!$C$8)/2 -> -0.131 | D93: =C93 -> -0.131 | E93: =Premissas!$C$9-Premissas!$C$8 -> 0.262 | F93: =SUM(C93:E93) -> 0
B94: Participação final | C94: =C92+C93 -> 0.3 | D94: =D92+D93 -> 0.3 | E94: =E92+E93 -> 0.4 | F94: =SUM(C94:E94) -> 1
B95: Fração alienada do investimento (13,1 ÷ 43,1) | C95: =-C93/C92 -> 0.30394432
B97: Ganho de capital no cash out (por holding) | C97: HIP. A — CUSTO ORIGINAL | D97: HIP. B — CUSTO INCREMENTADO
B98: Preço da venda | C98: =Premissas!$C$12 -> 600 | D98: =Premissas!$C$12 -> 600
B99: (−) Custo alocado (custo × fração alienada) | C99: =-C11*$C$95 -> -36.395508 | D99: =-C29*$C$95 -> -141.24721
B100: (=) Ganho de capital | C100: =C98+C99 -> 563.60449 | D100: =D98+D99 -> 458.75279
B101: IRPJ/CSLL (34%) | C101: =C100*Premissas!$C$10 -> 191.62553 | D101: =D100*Premissas!$C$10 -> 155.97595
B102: Líquido do imposto (preço − IR) | C102: =C98-C101 -> 408.37447 | D102: =D98-D101 -> 444.02405
B103: Custo remanescente (para a alienação futura) | C103: =C11+C99 -> 83.348492 | D103: =C29+D99 -> 323.4669
B105: CONCLUSÃO DO CASH OUT (TOTAL — 2 HOLDINGS)
B106: IRPJ/CSLL — Hipótese A | C106: =C101*2 -> 383.25105
B107: IRPJ/CSLL — Hipótese B | C107: =D101*2 -> 311.9519
B108: Economia da Hipótese B no cash out | C108: =C106-C107 -> 71.299159
B109: Operação única (primária + secundária simultâneas): no cash out prevalece o custo antigo — a Hipótese A é a leitura conservadora.
B111: 5. ALIENAÇÃO FUTURA — VENDA DO REMANESCENTE (30% POR HOLDING)
B112: Preço da venda futura — por holding (editável) | C112: 600
C113: HIP. A — CUSTO ORIGINAL | D113: HIP. B — CUSTO INCREMENTADO
B114: Custo remanescente | C114: =C103 -> 83.348492 | D114: =D103 -> 323.4669
...

Sheet Conclusão
B1: Conclusão — efeitos das duas hipóteses de custo
B3: SÍNTESE (TOTAL DAS 2 HOLDINGS — R$ MILHÕES)
C4: HIP. A — CUSTO ORIGINAL | D4: HIP. B — CUSTO INCREMENTADO | E4: Δ (ECONOMIA B)
B5: Custo do investimento após a incorporação | C5: =Contabilização!C11*2 -> 239.488 | D5: =Contabilização!C29*2 -> 929.42823 | E5: =D5-C5 -> 689.94023
B6: IRPJ/CSLL no cash out | C6: =Contabilização!C101*2 -> 383.25105 | D6: =Contabilização!D101*2 -> 311.9519 | E6: =C6-D6 -> 71.299159
B7: Custo remanescente para a alienação futura | C7: =Contabilização!C103*2 -> 166.69698 | D7: =Contabilização!D103*2 -> 646.9338 | E7: =D7-C7 -> 480.23682
B8: IRPJ/CSLL na alienação futura (preço editável da aba anterior) | C8: =Contabilização!C116*2 -> 351.32303 | D8: =Contabilização!D116*2 -> 188.04251 | E8: =C8-D8 -> 163.28052
B9: IRPJ/CSLL total (cash out + alienação futura) | C9: =C6+C8 -> 734.57408 | D9: =D6+D8 -> 499.9944 | E9: =C9-D9 -> 234.57968
B10: Benefício máximo da tese do custo "gordinho" (34% × parcela incorporada) | E10: =Contabilização!D28*Premissas!$C$10 -> 234.57968
B11: Check: economia no cash out + economia máxima na alienação − benefício máximo | E11: =E6+Contabilização!C120-E10 -> 0
B13: LEITURA
B14: Onde nasce a diferença | C14: Parcela incorporada de 345,0 por holding (690,0 no total) = reflexo do PL contábil da CNP (419,4) − diluição de 13,8% (74,4). Compõe custo na Hipótese B; não compõe na Hipótese A.
B15: Risco por camada | C15: Perda de diluição (33,0): menor controvérsia · reflexo do PL contábil da CNP (472,5): neutralidade defensável (MEP / variação de participação) · reflexo da parcela AVJ implícita (250,5): maior risco de requalificação.
B16: Enquadramento | C16: A definição CPC 15 x CPC 19 cabe ao auditor. Sob CPC 19, o AVJ fica "carimbado" a 34% em subconta e a Hipótese B deixa de existir.
