Workbook

Sheet Contexto
D2: Projeto Another House — Exercício da Incorporação sob CPC 15
D3: Duas hipóteses de custo do investimento: custo original ("magrinho") x custo incrementado ("gordinho")
B6: Base 30.06.2026 (com dividendos) · valores em R$ milhões · draft de trabalho — não constitui opinião legal
B8: O QUE ESTA PLANILHA DEMONSTRA
B9: Demonstração, etapa por etapa, dos efeitos contábeis e fiscais da incorporação da CNP Consórcio pela Embracon sob a premissa de COMBINAÇÃO DE NEGÓCIOS (CPC 15), com atos societários lavrados a valor patrimonial contábil (laudo art. 224 LSA): (1) situação antes; (2) incorporação e reflexo nas holdings, com a segregação de risco do custo do investimento (MLA); (3) cash out; (4) destinação do caixa (PJ x PF); (5) alienação futura. Em cada etapa com efeito fiscal, comparam-se as duas hipóteses de custo.
B13: AS DUAS HIPÓTESES DE CUSTO
B14: Hipótese A — custo original ("magrinho") | C14: O custo fiscal do investimento das holdings permanece o custo histórico (R$ 119,744 cada). A parcela incorporada (reflexo da incorporação) NÃO compõe custo — leitura de diferimento (jurisprudência recente do CARF: CPFL, Litela, Litel).
B15: Hipótese B — custo incrementado ("gordinho") | C15: A parcela incorporada líquida da diluição (R$ 344,970 por holding) integra o custo do investimento — leitura de exclusão definitiva do art. 33, §2º, do DL 1.598/77 (linha WTorre: o ganho neutralizado "dá custo").
B17: COMO LER / LEGENDA
B18: Células em AZUL | C18: Entradas/premissas editáveis (hardcoded). Tudo o mais é fórmula encadeada.
B19: Células em PRETO | C19: Fórmulas — o racional de cada número está na própria célula.
B20: Linhas "Check" | C20: Conferências (devem ser ~zero). Diferenças herdadas da base do draft estão apontadas e não foram "forçadas".
B22: CRITÉRIOS E NOTAS RELEVANTES
B23: 1. | C23: Valores adotados: aba "base 30 06 26com dividendos" do draft MLA (Exercicio_Incorporaçao_draft1). Balanços de 30.06.2026, em R$ milhões, já considerando dividendos de 120 declarados pela Embracon antes da incorporação.
B24: 2. | C24: Relação de troca: 13,8% para as Partes CNP (premissa do Acordo — EVs de R$ 821,9 mi x R$ 5.132,9 mi), e não a proporção dos PLs contábeis (22,2% x 77,8%). A incorporação é registrada a valor contábil (laudo art. 224 LSA).
B25: 3. | C25: AJUSTE DE CRITÉRIO vs. draft: o custo da participação alienada no cash out foi rateado pela FRAÇÃO alienada do investimento (13,1 p.p. ÷ 43,1 p.p. = 30,39%). O draft multiplicava o custo por 13,1% diretamente (custo alocado de 15,69 vs 36,40 na Hipótese A) — critério ajustado por ser o rateio proporcional o tecnicamente defensável.
B26: 4. | C26: Cash out: preço de 600 por holding (1.200 total, sem correções do SPA). Tese da "operação única" (primária + secundária simultâneas): no cash out prevalece o custo antigo — a Hipótese A é a leitura conservadora nesta etapa.
B27: 5. | C27: Segregação de risco do custo (MLA): o novo custo das holdings é aberto em 3 camadas — (i) investimento antigo (perda de diluição); (ii) reflexo do PL contábil da CNP; (iii) reflexo da parcela AVJ implícita (proporção do exemplo Deloitte: MV 300 ÷ VJ 866 = 34,64%) — "um tem mais risco que o outro".
B28: 6. | C28: Aba 4 (PJ x PF) usa as premissas do draft (IRRF dividendos 10%; CDI 12%; PJ a 100% do CDI com IR 34%; PF a 105% do CDI com IR 27%) — premissas a validar. Fórmula de rendimento corrigida para saldo × CDI × %CDI.
B29: 7. | C29: Checks de balanço: a base do draft tem diferenças de 0,34 (Embracon) e 0,84 (CNP) entre Ativos e Passivos+PL — mantidas e sinalizadas nas linhas "Check", a conciliar com o balancete.
B31: FONTES
B32: Draft MLA (Exercicio_Incorporaçao_draft1, aba "base 30 06 26com dividendos") · Acordo de Investimento de 20.10.2025 (13,8%; R$ 1,2 bi; 60/40) · Call Deloitte 17.08.2026 (exemplo VJ 866 / MV 300) · Calls e e-mails de ago/2026 (hipóteses "gordinho" x "magrinho", segregação de risco, operação única).

Sheet Premissas
B1: Premissas
B3: PREMISSAS GERAIS
B4: Data-base dos balanços | C4: 30.06.2026 | D4: Draft MLA — aba "base 30 06 26com dividendos"
B5: Unidade | C5: R$ milhões
B6: Participação das Partes CNP na incorporação (relação de troca) | C6: 0.138 | D6: Acordo: EV CNP 821,9 ÷ (821,9 + 5.132,9) = 13,8% — definitiva e irrevisável
B7: Participação-alvo final das Partes CNP | C7: 0.4 | D7: Acordo: 60% famílias (30/30) x 40% CNP
B8: IRPJ/CSLL — ganho de capital PJ | C8: 0.34
B9: Dividendos declarados pela Embracon antes da incorporação | C9: 120 | D9: Reduz o PL da Embracon a 239,488; permanece como passivo (a pagar às holdings)
B11: SEGREGAÇÃO DO CUSTO — PROPORÇÃO DO EXEMPLO DELOITTE (ILUSTRATIVO)
B12: Valor justo do PL da CNP (exemplo DTT) | C12: 866 | D12: Call Deloitte 17.08.2026 — números ilustrativos, não contratuais
B13: Mais-valia / AVJ contida no exemplo (MV) | C13: 300 | D13: Idem — parcela do VJ atribuída à reavaliação
B14: % AVJ implícito no PL da CNP | C14: =C13/C12 -> 0.34642032 | D14: MV ÷ VJ — aplicado ao PL contábil da CNP para segregar a camada de maior risco
B15: % contábil (sem AVJ) | C15: =1-C14 -> 0.65357968
B17: CASH OUT
B18: Preço por holding (venda à CNP Participações) | C18: 600 | D18: Total 1.200 (R$ 1,2 bi do SPA, sem IPCA/ajustes de caixa) — 50/50 Savian/JVFJ
B20: DESTINAÇÃO DO CAIXA E APLICAÇÕES (PREMISSAS DO DRAFT — A VALIDAR)
B21: IRRF sobre dividendos ao sócio PF | C21: 0.1 | D21: Premissa do draft (reforma tributária) — incide na distribuição da holding à PF
B22: CDI (a.a.) | C22: 0.12 | D22: Premissa do draft
B23: % do CDI — aplicação na PJ (holding) | C23: 1 | D23: Premissa do draft (100 do CDI)
B24: % do CDI — aplicação na PF | C24: 1.05 | D24: Premissa do draft (105 do CDI)
B25: IR sobre rendimentos — PJ | C25: 0.34 | D25: Premissa do draft (holding tributa o rendimento a 34%)
B26: IR sobre rendimentos — PF | C26: 0.27 | D26: Premissa do draft — a validar (renda fixa PF: 15%-22,5%)
B27: Horizonte de comparação (anos) | C27: 2 | D27: Premissa do draft
B29: Todas as células azuis desta aba alimentam as demais por fórmula. Alterando uma premissa, a planilha inteira recalcula.

Sheet 1. Situação Antes
B1: 1. Situação antes da incorporação — balanços 30.06.2026
B2: BALANÇOS DE PARTIDA (R$ MILHÕES) — BASE DRAFT MLA "COM DIVIDENDOS"
B4: SAVIAN | E4: JVFJ | H4: EMBRACON | K4: CNP CONSÓRCIO
B5: ATIVOS | C5: =SUM(C6:C10) -> 119.744 | E5: ATIVOS | F5: =SUM(F6:F10) -> 119.744 | H5: ATIVOS | I5: =SUM(I6:I10) -> 26138.03 | K5: ATIVOS | L5: =SUM(L6:L10) -> 17611.435
B6: Circulante | E6: Circulante | H6: Circulante | I6: 328.578 | K6: Circulante | L6: 945.234
B7: CPC 47 (despesas/comissões diferidas) | E7: CPC 47 (despesas/comissões diferidas) | H7: CPC 47 (despesas/comissões diferidas) | I7: 1937.402 | K7: CPC 47 (despesas/comissões diferidas) | L7: 216.353
B8: Permanente | E8: Permanente | H8: Permanente | I8: 57.986 | K8: Permanente | L8: 138.693
B9: Inv. Embracon | C9: =I18/2 -> 119.744 | E9: Inv. Embracon | F9: =I18/2 -> 119.744 | H9: Inv. Embracon | K9: Inv. Embracon
B10: Compensação (grupos de consórcio) | E10: Compensação (grupos de consórcio) | H10: Compensação (grupos de consórcio) | I10: 23814.064 | K10: Compensação (grupos de consórcio) | L10: 16311.155
B12: PASSIVOS | C12: =SUM(C13:C16) -> 0 | E12: PASSIVOS | F12: =SUM(F13:F16) -> 0 | H12: PASSIVOS | I12: =SUM(I13:I16) -> 25898.882 | K12: PASSIVOS | L12: =SUM(L13:L16) -> 16771.856
B13: Circulante | E13: Circulante | H13: Circulante | I13: 420.06 | K13: Circulante | L13: 232.757
B14: CPC 47 (receitas diferidas) | E14: CPC 47 (receitas diferidas) | H14: CPC 47 (receitas diferidas) | I14: 1544.758 | K14: CPC 47 (receitas diferidas) | L14: 227.944
B15: Dividendos a pagar | E15: Dividendos a pagar | H15: Dividendos a pagar | I15: =Premissas!C9 -> 120 | K15: Dividendos a pagar
B16: Compensação (grupos de consórcio) | E16: Compensação (grupos de consórcio) | H16: Compensação (grupos de consórcio) | I16: =I10 -> 23814.064 | K16: Compensação (grupos de consórcio) | L16: =L10 -> 16311.155
B18: PATRIMÔNIO LÍQUIDO | C18: =SUM(C19:C21) -> 119.744 | E18: PATRIMÔNIO LÍQUIDO | F18: =SUM(F19:F21) -> 119.744 | H18: PATRIMÔNIO LÍQUIDO | I18: =SUM(I19:I21) -> 239.488 | K18: PATRIMÔNIO LÍQUIDO | L18: =SUM(L19:L21) -> 838.735
B19: Capital | C19: =C9 -> 119.744 | E19: Capital | F19: =F9 -> 119.744 | H19: Capital | I19: 85 | K19: Capital | L19: 519
B20: Reservas | E20: Reservas | H20: Reservas | I20: 274.488 | K20: Reservas | L20: 319.735
B21: (−) Dividendos declarados | E21: (−) Dividendos declarados | H21: (−) Dividendos declarados | I21: =-Premissas!C9 -> -120 | K21: (−) Dividendos declarados
B23: PASSIVOS + PL | C23: =C12+C18 -> 119.744 | E23: PASSIVOS + PL | F23: =F12+F18 -> 119.744 | H23: PASSIVOS + PL | I23: =I12+I18 -> 26138.37 | K23: PASSIVOS + PL | L23: =L12+L18 -> 17610.591
B24: Check (Ativos − Passivos − PL) | C24: =C5-C23 -> 0 | E24: Check (Ativos − Passivos − PL) | F24: =F5-F23 -> 0 | H24: Check (Ativos − Passivos − PL) | I24: =I5-I23 -> -0.34 | K24: Check (Ativos − Passivos − PL) | L24: =L5-L23 -> 0.844
B27: PROPORCIONALIDADE DOS PLs "NOMINAIS"
B28: Entidade | C28: PL 30.06.26 | D28: % do PL combinado
B29: Embracon | C29: =I18 -> 239.488 | D29: =C29/C31 -> 0.22211361
B30: CNP Consórcio | C30: =L18 -> 838.735 | D30: =C30/C31 -> 0.77788639
B31: PL combinado | C31: =C29+C30 -> 1078.223 | D31: =C31/C31 -> 1
B33: A relação de troca contratual (13,8% / 86,2%) NÃO segue a proporção dos PLs contábeis acima (22,2% / 77,8%): decorre dos EVs acordados no Acordo (CNP 821,9 x Embracon 5.132,9). É exatamente esse descolamento que gera a "parcela incorporada" nas holdings e a discussão de custo.

Sheet 2. Incorporação CPC 15
B1: 2. Incorporação da CNP pela Embracon (CPC 15 — atos a valor contábil)
B3: RELAÇÃO DE TROCA E PARTICIPAÇÕES | H3: EMBRACON COMBINADA — BALANÇO APÓS (VALOR CONTÁBIL)
B4: Acionista | C4: Antes | D4: Após incorporação | H4: Linha | I4: Embracon | J4: CNP | K4: Combinada
B5: Cia. Savian | C5: 0.5 | D5: =C5*(1-Premissas!C6) -> 0.431 | H5: Ativo circulante | I5: ='1. Situação Antes'!I6 -> 328.578 | J5: ='1. Situação Antes'!L6 -> 945.234 | K5: =I5+J5 -> 1273.812
B6: Cia. JVFJ | C6: 0.5 | D6: =C6*(1-Premissas!C6) -> 0.431 | H6: Ativo CPC 47 | I6: ='1. Situação Antes'!I7 -> 1937.402 | J6: ='1. Situação Antes'!L7 -> 216.353 | K6: =I6+J6 -> 2153.755
B7: Partes CNP (ações novas) | C7: 0 | D7: =Premissas!C6 -> 0.138 | H7: Permanente | I7: ='1. Situação Antes'!I8 -> 57.986 | J7: ='1. Situação Antes'!L8 -> 138.693 | K7: =I7+J7 -> 196.679
B8: Total | C8: =SUM(C5:C7) -> 1 | D8: =SUM(D5:D7) -> 1 | H8: Compensação (ativo) | I8: ='1. Situação Antes'!I10 -> 23814.064 | J8: ='1. Situação Antes'!L10 -> 16311.155 | K8: =I8+J8 -> 40125.219
H9: Passivo circulante | I9: ='1. Situação Antes'!I13 -> 420.06 | J9: ='1. Situação Antes'!L13 -> 232.757 | K9: =I9+J9 -> 652.817
B10: REFLEXO NAS HOLDINGS (MEP) — CUSTO DO INVESTIMENTO | H10: Passivo CPC 47 | I10: ='1. Situação Antes'!I14 -> 1544.758 | J10: ='1. Situação Antes'!L14 -> 227.944 | K10: =I10+J10 -> 1772.702
B11: Item | C11: Por holding | D11: Total (2 holdings) | H11: Dividendos a pagar | I11: ='1. Situação Antes'!I15 -> 120 | J11: ='1. Situação Antes'!L15 -> 0 | K11: =I11+J11 -> 120
B12: Investimento anterior (custo original — "magrinho") | C12: ='1. Situação Antes'!C9 -> 119.744 | D12: =C12*2 -> 239.488 | H12: Compensação (passivo) | I12: ='1. Situação Antes'!I16 -> 23814.064 | J12: ='1. Situação Antes'!L16 -> 16311.155 | K12: =I12+J12 -> 40125.219
B13: (+) Incorporação base (reflexo do PL contábil da CNP ÷ 2) | C13: ='1. Situação Antes'!L18/2 -> 419.3675 | D13: =C13*2 -> 838.735 | H13: Capital social | I13: ='1. Situação Antes'!I19 -> 85 | J13: ='1. Situação Antes'!L19 -> 519 | K13: =I13+J13 -> 604
B14: (−) Diluição (13,8% sobre investimento + base) | C14: =-(C12+C13)*Premissas!C6 -> -74.397387 | D14: =C14*2 -> -148.79477 | H14: Reservas | I14: ='1. Situação Antes'!I20 -> 274.488 | J14: ='1. Situação Antes'!L20 -> 319.735 | K14: =I14+J14 -> 594.223
B15: (=) Parcela incorporada (líquida) | C15: =C13+C14 -> 344.97011 | D15: =C15*2 -> 689.94023 | H15: (−) Dividendos | I15: ='1. Situação Antes'!I21 -> -120 | J15: ='1. Situação Antes'!L21 -> 0 | K15: =I15+J15 -> -120
B16: (=) Custo final do investimento ("gordinho") | C16: =C12+C15 -> 464.71411 | D16: =C16*2 -> 929.42823 | H16: PL combinado | I16: ='1. Situação Antes'!I18 -> 239.488 | J16: ='1. Situação Antes'!L18 -> 838.735 | K16: =I16+J16 -> 1078.223
B17: Check: 43,1% × PL combinado | C17: =D5*K16-C16 -> 0 | H17: Check (A − P − PL) | I17: =SUM(I5:I8)-SUM(I9:I12)-I16 -> -0.34 | J17: =SUM(J5:J8)-SUM(J9:J12)-J16 -> 0.844 | K17: =SUM(K5:K8)-SUM(K9:K12)-K16 -> 0.504
B19: LANÇAMENTOS CONTÁBEIS NAS HOLDINGS (CADA UMA) | H19: LADO CNP HOLDING (INFORMATIVO)
B20: Lançamento | C20: Débito | D20: Crédito | E20: Contrapartida / natureza | H20: Baixa do acervo vertido (PL CNP) | I20: =-'1. Situação Antes'!L18 -> -838.735
B21: 1. Reflexo da incorporação — Inv. Embracon | C21: =C13 -> 419.3675 | E21: Conta patrimonial (ORA x reserva — EM ABERTO; CPC não define; Deloitte não respondeu) | H21: Participação recebida (13,8% × PL combinado) | I21: =Premissas!C6*K16 -> 148.79477
B22: 2. Perda de diluição — Inv. Embracon | D22: =-C14 -> 74.397387 | E22: Resultado de equivalência (variação de participação, art. 33, §2º, DL 1.598/77) | H22: Resultado contábil a valor contábil | I22: =I20+I21 -> -689.94023
B23: Efeito líquido no investimento | C23: =C21-D22 -> 344.97011 | E23: (igual à parcela incorporada) | H23: Espelho da parcela incorporada das holdings (−689,94). É esta perda a valor contábil que leva a CNP a defender a joint operation (CPC 19) com remensuração a valor justo em resultado.
B25: SEGREGAÇÃO DE RISCO DO CUSTO (MLA) — 3 CAMADAS
B26: Camada | C26: PL combinado | D26: Antes (86,2%→) | E26: Depois (×86,2%) | F26: Δ (2 holdings)
B27: 1. Investimento antigo (PL Embracon) — perda de diluição | C27: ='1. Situação Antes'!I18 -> 239.488 | D27: =C27 -> 239.488 | E27: =C27*(1-Premissas!C6) -> 206.43866 | F27: =E27-D27 -> -33.049344
B28: 2. Reflexo do PL contábil da CNP (menor risco) | C28: ='1. Situação Antes'!L18*Premissas!C15 -> 548.18015 | D28: 0 | E28: =C28*(1-Premissas!C6) -> 472.53129 | F28: =E28-D28 -> 472.53129
B29: 3. Reflexo da parcela AVJ implícita (maior risco) | C29: ='1. Situação Antes'!L18*Premissas!C14 -> 290.55485 | D29: 0 | E29: =C29*(1-Premissas!C6) -> 250.45828 | F29: =E29-D29 -> 250.45828
B30: Novo Embracon (soma) | C30: =SUM(C27:C29) -> 1078.223 | D30: =SUM(D27:D29) -> 239.488 | E30: =SUM(E27:E29) -> 929.42823 | F30: =SUM(F27:F29) -> 689.94023
B31: Δ por holding (÷2) — deve igualar a parcela incorporada | F31: =F30/2-C15 -> 0
B33: Sob CPC 15 "pleno" haveria PPA com laudo a valor justo do PL da CNP (mais-valia "grudando" nos ativos). Neste exercício, seguindo o draft e o contrato (laudo a valor patrimonial contábil, art. 224 LSA), a incorporação é registrada a valor contábil e a dimensão CPC 15 aparece na segregação de risco acima — premissa da Malu: todo o excedente é mais-valia/AVJ, sem goodwill.

Sheet 3. Cash Out
B1: 3. Cash out — venda de 26,2% à CNP (etapa 2, simultânea)
B3: PARÂMETROS DA ETAPA
B4: Pontos percentuais vendidos — total (40% − 13,8%) | C4: =Premissas!C7-Premissas!C6 -> 0.262
B5: Pontos percentuais vendidos — por holding | C5: =C4/2 -> 0.131
B6: Participação de cada holding após a incorporação | C6: ='2. Incorporação CPC 15'!D5 -> 0.431
B7: Fração alienada do investimento (13,1 ÷ 43,1) | C7: =C5/C6 -> 0.30394432
B8: Preço por holding | C8: =Premissas!C18 -> 600
B10: PARTICIPAÇÕES: APÓS INCORPORAÇÃO → VENDA → FINAL
B11: Acionista | C11: Após incorp. | D11: Venda | F11: Final
B12: Cia. Savian | C12: ='2. Incorporação CPC 15'!D5 -> 0.431 | D12: =-$C$5 -> -0.131 | F12: =C12+D12 -> 0.3
B13: Cia. JVFJ | C13: ='2. Incorporação CPC 15'!D6 -> 0.431 | D13: =-$C$5 -> -0.131 | F13: =C13+D13 -> 0.3
B14: Partes CNP | C14: ='2. Incorporação CPC 15'!D7 -> 0.138 | D14: =$C$4 -> 0.262 | F14: =C14+D14 -> 0.4
B15: Total | C15: =SUM(C12:C14) -> 1 | D15: =SUM(D12:D14) -> 0 | F15: =SUM(F12:F14) -> 1
B17: GANHO DE CAPITAL — DUAS HIPÓTESES DE CUSTO
C18: Por holding | F18: Total (2 holdings)
B19: Item | C19: Hip. A — custo original | D19: Hip. B — custo incrementado | F19: Hip. A | G19: Hip. B
B20: Preço da alienação | C20: =$C$8 -> 600 | D20: =$C$8 -> 600 | F20: =C20*2 -> 1200 | G20: =D20*2 -> 1200
B21: Custo total do investimento | C21: ='2. Incorporação CPC 15'!C12 -> 119.744 | D21: ='2. Incorporação CPC 15'!C16 -> 464.71411 | F21: =C21*2 -> 239.488 | G21: =D21*2 -> 929.42823
B22: Custo alocado à parcela alienada (× fração 30,39%) | C22: =C21*$C$7 -> 36.395508 | D22: =D21*$C$7 -> 141.24721 | F22: =C22*2 -> 72.791016 | G22: =D22*2 -> 282.49443
B23: Ganho de capital | C23: =C20-C22 -> 563.60449 | D23: =D20-D22 -> 458.75279 | F23: =C23*2 -> 1127.209 | G23: =D23*2 -> 917.50557
B24: IRPJ/CSLL (34%) | C24: =C23*Premissas!C8 -> 191.62553 | D24: =D23*Premissas!C8 -> 155.97595 | F24: =C24*2 -> 383.25105 | G24: =D24*2 -> 311.9519
B25: Líquido do imposto (preço − IR) | C25: =C20-C24 -> 408.37447 | D25: =D20-D24 -> 444.02405 | F25: =C25*2 -> 816.74895 | G25: =D25*2 -> 888.0481
B26: Alíquota efetiva sobre o preço | C26: =C24/C20 -> 0.31937588 | D26: =D24/D20 -> 0.25995991 | F26: =F24/F20 -> 0.31937588 | G26: =G24/G20 -> 0.25995991
B27: Custo remanescente (para a alienação futura) | C27: =C21-C22 -> 83.348492 | D27: =D21-D22 -> 323.4669 | F27: =C27*2 -> 166.69698 | G27: =D27*2 -> 646.9338
B28: Economia de IR da Hipótese B nesta etapa | C28: =C24-D24 -> 35.64958 | F28: =F24-G24 -> 71.299159
B30: Tese da "operação única": incorporação e cash out simultâneos formam um só negócio — no cash out prevaleceria o CUSTO ANTIGO (Hipótese A), sem aproveitamento da parcela incorporada. A Hipótese B pressupõe que a parcela incorporada compõe custo já nesta etapa (art. 33, §2º, como exclusão definitiva — WTorre). Preço de 600 por holding sem correções do SPA (IPCA + ajustes de caixa líquido + earn-out de até 680 não modelados).

Sheet 4. Caixa PJ x PF
B1: 4. Destinação do caixa do cash out — manter na PJ x distribuir à PF
B3: PONTO DE PARTIDA (POR HOLDING — HIPÓTESE A, CONSERVADORA)
B4: Líquido do cash out na holding (após IR de 34%) | C4: ='3. Cash Out'!C25 -> 408.37447 | E4: Aba 3, Hipótese A (custo original)
B5: IRRF na distribuição de dividendos à PF (10%) | C5: =C4*Premissas!C21 -> 40.837447 | E5: Premissa do draft (reforma tributária)
B6: Líquido disponível na PF | C6: =C4-C5 -> 367.53703
B8: APLICAÇÃO FINANCEIRA — 2 ANOS (PREMISSAS DO DRAFT)
B9: Item | C9: Manter na PJ | D9: Distribuir à PF | E9: Racional
B10: Saldo inicial | C10: =C4 -> 408.37447 | D10: =C6 -> 367.53703 | E10: PJ mantém 100%; PF recebe líquido do IRRF de 10%
B11: Ano 1 — rendimento bruto | C11: =C10*Premissas!C22*Premissas!C23 -> 49.004937 | D11: =D10*Premissas!C22*Premissas!C24 -> 46.309665 | E11: saldo × CDI × % do CDI (PJ 100% · PF 105%)
B12: Ano 1 — IR sobre o rendimento | C12: =-C11*Premissas!C25 -> -16.661678 | D12: =-D11*Premissas!C26 -> -12.50361 | E12: PJ 34% · PF 27% (draft — a validar)
B13: Saldo ao fim do ano 1 | C13: =SUM(C10:C12) -> 440.71773 | D13: =SUM(D10:D12) -> 401.34308
B14: Ano 2 — rendimento bruto | C14: =C13*Premissas!C22*Premissas!C23 -> 52.886128 | D14: =D13*Premissas!C22*Premissas!C24 -> 50.569228
B15: Ano 2 — IR sobre o rendimento | C15: =-C14*Premissas!C25 -> -17.981283 | D15: =-D14*Premissas!C26 -> -13.653692
B16: Saldo ao fim do ano 2 | C16: =SUM(C13:C15) -> 475.62258 | D16: =SUM(D13:D15) -> 438.25862
B17: Vantagem de manter na PJ (fim do ano 2) | C17: =C16-D16 -> 37.363958
B19: Leitura: distribuir à PF custa 10% de IRRF na largada; a PF aplica a 105% do CDI com IR menor (27% vs 34%), mas em 2 anos não recupera a perda inicial — a PJ termina à frente. Premissas do draft a validar (IR de PF em renda fixa é 15%–22,5% conforme prazo; a comparação é sensível a essas alíquotas e ao horizonte). Sob CPC 19/AVJ diferido, "subir pra física" fica ainda mais custoso (ganho carimbado nas holdings).

Sheet 5. Alienação Futura
B1: 5. Alienação futura ("passo F") — sensibilidade de preço
B3: BASE (POR HOLDING)
B4: Participação remanescente | C4: ='3. Cash Out'!F12 -> 0.3
B5: Custo remanescente — Hip. A (custo original) | C5: ='3. Cash Out'!C27 -> 83.348492
B6: Custo remanescente — Hip. B (custo incrementado) | C6: ='3. Cash Out'!D27 -> 323.4669
B7: Diferença de custo (B − A) | C7: =C6-C5 -> 240.11841
B9: SENSIBILIDADE — PREÇO DA VENDA FUTURA (POR HOLDING, R$ MILHÕES)
B10: Preço da venda futura (editável) | C10: 300 | D10: 600 | E10: 900 | F10: 1200 | G10: 1500
B11: Ganho de capital — Hip. A | C11: =C10-$C$5 -> 216.65151 | D11: =D10-$C$5 -> 516.65151 | E11: =E10-$C$5 -> 816.65151 | F11: =F10-$C$5 -> 1116.6515 | G11: =G10-$C$5 -> 1416.6515
B12: IRPJ/CSLL 34% — Hip. A | C12: =MAX(0,C11)*Premissas!C8 -> 73.661513 | D12: =MAX(0,D11)*Premissas!C8 -> 175.66151 | E12: =MAX(0,E11)*Premissas!C8 -> 277.66151 | F12: =MAX(0,F11)*Premissas!C8 -> 379.66151 | G12: =MAX(0,G11)*Premissas!C8 -> 481.66151
B13: Ganho de capital — Hip. B | C13: =C10-$C$6 -> -23.4669 | D13: =D10-$C$6 -> 276.5331 | E13: =E10-$C$6 -> 576.5331 | F13: =F10-$C$6 -> 876.5331 | G13: =G10-$C$6 -> 1176.5331
B14: IRPJ/CSLL 34% — Hip. B | C14: =MAX(0,C13)*Premissas!C8 -> 0 | D14: =MAX(0,D13)*Premissas!C8 -> 94.021254 | E14: =MAX(0,E13)*Premissas!C8 -> 196.02125 | F14: =MAX(0,F13)*Premissas!C8 -> 298.02125 | G14: =MAX(0,G13)*Premissas!C8 -> 400.02125
B15: Economia de IR da Hip. B (A − B) | C15: =C12-C14 -> 73.661513 | D15: =D12-D14 -> 81.640259 | E15: =E12-E14 -> 81.640259 | F15: =F12-F14 -> 81.640259 | G15: =G12-G14 -> 81.640259
B16: Idem, total 2 holdings | C16: =C15*2 -> 147.32303 | D16: =D15*2 -> 163.28052 | E16: =E15*2 -> 163.28052 | F16: =F15*2 -> 163.28052 | G16: =G15*2 -> 163.28052
B18: A economia da Hipótese B tende ao teto de 34% × diferença de custo (81,64 por holding; 163,28 nas duas) e independe do preço enquanto o ganho for positivo nas duas hipóteses (preços baixos limitam o efeito — IR não fica negativo). Não há preço definido para o passo F: a linha de preço é editável. Sob CPC 19, o AVJ fica "carimbado" a 34% em subconta — economicamente equivalente à Hipótese A, com tributação garantida na realização.

Sheet Conclusão
B1: Conclusão — síntese das duas hipóteses de custo
B3: SÍNTESE (TOTAL DAS 2 HOLDINGS, R$ MILHÕES)
B4: Item | C4: Hip. A — custo original | D4: Hip. B — custo incrementado | E4: Δ (economia B)
B5: Custo total do investimento após a incorporação | C5: ='2. Incorporação CPC 15'!C12*2 -> 239.488 | D5: ='2. Incorporação CPC 15'!C16*2 -> 929.42823 | E5: =D5-C5 -> 689.94023
B6: IR no cash out (etapa 3) | C6: ='3. Cash Out'!F24 -> 383.25105 | D6: ='3. Cash Out'!G24 -> 311.9519 | E6: =C6-D6 -> 71.299159
B7: Custo remanescente para o passo F | C7: ='3. Cash Out'!C27*2 -> 166.69698 | D7: ='3. Cash Out'!D27*2 -> 646.9338 | E7: =D7-C7 -> 480.23682
B8: Economia futura máxima da Hip. B (34% × Δ custo remanescente) | E8: =E7*Premissas!C8 -> 163.28052
B9: BENEFÍCIO TOTAL DA TESE DO CUSTO "GORDINHO" | E9: =E6+E8 -> 234.57968
B10: Check: 34% × parcela incorporada total (689,94) | E10: =E9-'2. Incorporação CPC 15'!D15*Premissas!C8 -> 0
B12: LEITURA E RISCOS
B13: Onde nasce a diferença | C13: A parcela incorporada (344,97 por holding; 689,94 no total) = reflexo do PL contábil da CNP (419,37) − diluição de 13,8% (74,40). Compõe custo na Hip. B; não compõe na Hip. A.
B14: Valor da tese | C14: 34% × 689,94 = 234,58 no total — sendo 71,30 já no cash out (fração alienada de 30,39%) e até 163,28 na alienação futura (fração retida de 69,61%).
B15: Riscos por camada | C15: Perda de diluição (33,05): menor controvérsia. Reflexo do PL contábil da CNP (472,53): neutralidade defensável (MEP/variação de participação). Reflexo da parcela AVJ implícita (250,46): maior risco de requalificação (AVJ Reflexo — tributação na alienação).
B16: Jurisprudência | C16: WTorre (1402-004.537/2020) suporta a exclusão definitiva ("dá custo"); CPFL, Litela e Litel (2024) apontam diferimento — tributa quando o ganho migra de ORA/reserva para a DRE. A conta de PL da contrapartida (ORA x reserva) segue indefinida.
B17: Quem decide o enquadramento | C17: O auditor da Embracon (Deloitte) define CPC 15 x CPC 19. Sob CPC 19, o AVJ fica carimbado a 34% em subconta e a Hip. B deixa de existir; "cai a tese do MEP".
